hytek_parser/__init__.py
hytek_parser/_utils.py
hytek_parser/export_xls/__init__.py
hytek_parser/export_xls/_utils.py
hytek_parser/export_xls/schemas.py
hytek_parser/hy3/__init__.py
hytek_parser/hy3/_utils.py
hytek_parser/hy3/enums.py
hytek_parser/hy3/line_parsers/__init__.py
hytek_parser/hy3/line_parsers/a_file_parsers.py
hytek_parser/hy3/line_parsers/b_meet_parsers.py
hytek_parser/hy3/line_parsers/c_team_parsers.py
hytek_parser/hy3/line_parsers/d_swimmer_parsers.py
hytek_parser/hy3/line_parsers/e_event_parsers.py
hytek_parser/hy3/line_parsers/f_relay_parsers.py
hytek_parser/hy3/line_parsers/g_split_parsers.py
hytek_parser/hy3/line_parsers/h_dq_parsers.py
hytek_parser/hy3/schemas.py
hytek_parser/hy3_parser.py
hytek_parser/hyv/__init__.py
hytek_parser/hyv/enums.py
hytek_parser/hyv/schemas.py
hytek_parser/py.typed
hytek_parser/types.py
hytek_parser-1.2.0.dist-info/LICENSE.md
hytek_parser-1.2.0.dist-info/METADATA
hytek_parser-1.2.0.dist-info/WHEEL
hytek_parser-1.2.0.dist-info/RECORD
