Metadata-Version: 2.1
Name: hytek-parser
Version: 1.2.0
Summary: Parsers for the files produced by Hytek's Meet Manager.
Home-page: https://www.github.com/SwimComm/hytek-parser
License: MIT
Keywords: hytek,parsers,hy3
Author: Nino Maruszewski
Author-email: nino.maruszewski@hotmail.com
Requires-Python: >=3.9,<4.0
Classifier: Development Status :: 5 - Production/Stable
Classifier: Intended Audience :: Developers
Classifier: License :: OSI Approved :: MIT License
Classifier: Operating System :: OS Independent
Classifier: Programming Language :: Python :: 3
Classifier: Programming Language :: Python :: 3.9
Classifier: Programming Language :: Python :: 3.10
Classifier: Programming Language :: Python :: 3.11
Classifier: Programming Language :: Python :: 3.12
Classifier: Topic :: Text Processing
Classifier: Typing :: Typed
Requires-Dist: aenum (>=3.1.8,<4.0.0)
Requires-Dist: attrs (>=21.4.0,<22.0.0)
Requires-Dist: xlrd (>=2.0.1,<3.0.0)
Project-URL: Bug Tracker, https://www.github.com/SwimComm/hytek-parser/issues
Project-URL: Documentation, https://www.github.com/SwimComm/hytek-parser
Project-URL: Repository, https://www.github.com/SwimComm/hytek-parser
